rri/__init__.py
rri/exception.py
rri/rri.py
rri-0.1.2.dist-info/LICENSE
rri-0.1.2.dist-info/METADATA
rri-0.1.2.dist-info/WHEEL
rri-0.1.2.dist-info/top_level.txt
rri-0.1.2.dist-info/RECORD
