Metadata-Version: 2.1
Name: rri
Version: 0.1.2
Summary: Client library for the ICANN Registry Reporting Interface
Home-page: https://github.com/storeyio/rri
Author: John Storey
Author-email: hello@storey.io
License: MIT license
Keywords: rri icann registry api
Platform: UNKNOWN
Classifier: Development Status :: 3 - Alpha
Classifier: Intended Audience :: Developers
Classifier: License :: OSI Approved :: MIT License
Classifier: Natural Language :: English
Classifier: Topic :: Software Development :: Libraries
Classifier: Programming Language :: Python :: 3
Classifier: Programming Language :: Python :: 3.6
Classifier: Programming Language :: Python :: 3.7
Requires-Python: >=3.6.0
Requires-Dist: requests (<3.0.0,>=2.19.1)
Requires-Dist: uritemplate (==3.0.0)
